__init__.py
cythonbuilder/__init__.py
cythonbuilder/__main__.py
cythonbuilder/appsettings.py
cythonbuilder/cli.py
cythonbuilder/cython_builder.py
cythonbuilder/definitions.py
cythonbuilder/helpers.py
cythonbuilder/logs.py
cythonbuilder/pyigenerator.py
cythonbuilder-0.1.24.dist-info/METADATA
cythonbuilder-0.1.24.dist-info/WHEEL
cythonbuilder-0.1.24.dist-info/entry_points.txt
cythonbuilder-0.1.24.dist-info/top_level.txt
cythonbuilder-0.1.24.dist-info/RECORD
