Metadata-Version: 2.1
Name: cythonbuilder
Version: 0.1.24
Summary: CythonBuilder; automated compiling and packaging of Cython code
Author-email: Mike Huls <mikehuls42@gmail.com>
Project-URL: Homepage, https://github.com/mike-huls/cythonbuilder
Project-URL: Bug Tracker, https://github.com/mike-huls/cythonbuilder/issues
Project-URL: Documentation, https://github.com/mike-huls/cythonbuilder/blob/main/README.md/
Project-URL: Source, https://github.com/mike-huls/cythonbuilder/
Project-URL: Say Thanks!, https://www.buymeacoffee.com/mikehuls
Keywords: pypi,Cython,setup,packaging,compilation
Classifier: Environment :: Console
Classifier: Operating System :: OS Independent
Classifier: Topic :: Software Development :: Libraries :: Python Modules
Classifier: Topic :: Software Development :: Build Tools
Classifier: Development Status :: 5 - Production/Stable
Classifier: Intended Audience :: Developers
Classifier: Intended Audience :: Information Technology
Classifier: Intended Audience :: System Administrators
Classifier: License :: OSI Approved :: MIT License
Classifier: Topic :: Software Development :: Libraries :: Python Modules
Classifier: Topic :: Software Development :: Libraries
Classifier: Topic :: Software Development
Classifier: Programming Language :: Cython
Classifier: Programming Language :: Python
Classifier: Programming Language :: Python :: 3
Classifier: Programming Language :: Python :: 3 :: Only
Classifier: Programming Language :: Python :: 3.9
Classifier: Programming Language :: Python :: 3.10
Classifier: Programming Language :: Python :: 3.11
Classifier: Programming Language :: Python :: 3.12
Classifier: Programming Language :: Python :: 3.13
Classifier: Programming Language :: Python :: Implementation :: CPython
Classifier: Programming Language :: Cython
Requires-Python: >=3.9
Requires-Dist: cython >=3.0.11
Requires-Dist: typer >=0.12.5
